3_SYN/5_SYN/4_COMB_LOGIC/2_ENCODER/Interrupt_Controller.v
`timescale 1ns / 1ps

module interrupt_controller (

	i_int	,
	i_ack	,
	o_id	,
	o_req

);

input [7:0]	i_int	     ;
input		i_ack	     ;

output  [2:0]	o_id	     ;
output  	o_req	     ;

reg [7:0] r_active_int 	     ;

reg [2:0] o_id	             ;
reg	  o_req	             ;

always @(*) begin
	o_id = 3'b000        ;
	o_req = 1'b0         ;
	r_active_int = i_int ;

	if (i_ack) begin
	    r_active_int = 8'b0000_0000;
	end else begin
	    casex (r_active_int)
		8'b1xxx_xxxx	: begin o_id = 3'b111; o_req = 1'b1; end
	        8'b01xx_xxxx    : begin o_id = 3'b110; o_req = 1'b1; end
		8'b001x_xxxx	: begin o_id = 3'b101; o_req = 1'b1; end 
		8'b0001_xxxx	: begin o_id = 3'b100; o_req = 1'b1; end
		8'b0000_1xxx	: begin o_id = 3'b011; o_req = 1'b1; end
		8'b0000_01xx	: begin o_id = 3'b010; o_req = 1'b1; end
		8'b0000_001x	: begin o_id = 3'b001; o_req = 1'b1; end
		8'b0000_0001	: begin o_id = 3'b000; o_req = 1'b1; end
		default		: begin o_id = 3'b000; o_req = 1'b0; end

		endcase
	end
end
		

endmodule

3_SYN/5_SYN/4_COMB_LOGIC/2_ENCODER/tb_Interrupt_Controller.v
`timescale 1ns / 1ps

module tb_interrupt_controller;

reg [7:0]  i_int	;
reg 	   i_ack	;

wire [2:0] o_id		;
wire 	   o_req	;

interrupt_controller uut (
	.i_int	(i_int  )	,
	.i_ack	(i_ack	)	,
	.o_id	(o_id	)	,
	.o_req	(o_req	)	
);

initial begin
	$dumpfile("./interrupt_controller.vcd") ;
	$dumpvars(0, tb_interrupt_controller)	;
end

initial begin

	$monitor("Time = %0t | i_int=%b | i_ack=%b | o_id = %b | o_req=%b", $time, i_int, i_ack, o_id, o_req);

i_int		= 8'b0000_0000 ;
i_ack		= 1'b0	       ;

#10 i_int 	= 8'b0000_0001 ;
#10 i_int 	= 8'b0010_0000 ;
#10 i_int	= 8'b1000_0000 ;
#10 i_ack 	= 1'b1	       ;
#10 i_ack 	= 1'b0	       ;

#10 i_int  	= 8'b0100_0010 ;
#10 i_ack 	= 1'b1	       ;
#10 i_ack 	= 1'b0	       ;

#10 i_int 	= 8'b0000_0000 ;

#20 $finish;

end

endmodule

1_RTL/4_COMB_LOGIC/2_ENCODER/interrupt_controller.vcd
$date
    Jul  1, 2026  01:46:05
$end
$version
    TOOL:	xmsim(64)	22.03-s012
$end
$timescale
    1 ps
$end

$scope module tb_interrupt_controller $end
$var reg       8 !    i_int [7:0] $end
$var reg       1 "    i_ack $end
$var wire      3 #    o_id [2:0] $end
$var wire      1 $    o_req  $end

$scope module uut $end
$var wire      8 %    i_int [7:0] $end
$var wire      1 &    i_ack  $end
$var reg       3 '    o_id [2:0] $end
$var reg       1 (    o_req $end
$var reg       8 )    r_active_int [7:0] $end
$upscope $end

$upscope $end

$enddefinitions $end
$dumpvars
b0 !
0"
b0 #
0$
b0 %
0&
b0 '
0(
b0 )
$end
#10000
b1 !
b1 %
b1 )
1(
1$
#20000
b100000 !
b100000 %
0(
b100000 )
b101 '
1(
b101 #
#30000
b10000000 !
b10000000 %
b0 '
0(
b10000000 )
b111 '
1(
b111 #
#40000
1"
1&
b0 '
0(
b0 )
0$
b0 #
#50000
0"
0&
b10000000 )
b111 '
1(
1$
b111 #
#60000
b1000010 !
b1000010 %
b0 '
0(
b1000010 )
b110 '
1(
b110 #
#70000
1"
1&
b0 '
0(
b0 )
0$
b0 #
#80000
0"
0&
b1000010 )
b110 '
1(
1$
b110 #
#90000
b0 !
b0 %
b0 '
0(
b0 )
0$
b0 #
